LICENSE.txt
MANIFEST.in
README.rst
pyproject.toml
setup.cfg
setup.py
pycursorsio/__init__.py
pycursorsio/__main__.py
pycursorsio/cli.py
pycursorsio/client.py
pycursorsio/m28n.py
pycursorsio/state.py
pycursorsio/utils.py
pycursorsio.egg-info/PKG-INFO
pycursorsio.egg-info/SOURCES.txt
pycursorsio.egg-info/dependency_links.txt
pycursorsio.egg-info/not-zip-safe
pycursorsio.egg-info/requires.txt
pycursorsio.egg-info/top_level.txt
pycursorsio/assets/NovaSquare.ttf
pycursorsio/assets/cursor.png
pycursorsio/assets/favicon.ico